depscan/__init__.py
depscan/cli.py
depscan/cli_options.py
depscan/lib/__init__.py
depscan/lib/audit.py
depscan/lib/bom.py
depscan/lib/config.py
depscan/lib/explainer.py
depscan/lib/github.py
depscan/lib/license.py
depscan/lib/logger.py
depscan/lib/tomlparse.py
depscan/lib/utils.py
depscan/lib/package_query/__init__.py
depscan/lib/package_query/cargo_pkg.py
depscan/lib/package_query/metadata.py
depscan/lib/package_query/npm_pkg.py
depscan/lib/package_query/pkg_query.py
depscan/lib/package_query/pypi_pkg.py
owasp_depscan-6.0.0.dist-info/licenses/LICENSE
vendor/__init__.py
vendor/choosealicense.com/_data/fields.yml
vendor/choosealicense.com/_data/meta.yml
vendor/choosealicense.com/_data/rules.yml
vendor/choosealicense.com/_licenses/0bsd.txt
vendor/choosealicense.com/_licenses/afl-3.0.txt
vendor/choosealicense.com/_licenses/agpl-3.0.txt
vendor/choosealicense.com/_licenses/apache-2.0.txt
vendor/choosealicense.com/_licenses/artistic-2.0.txt
vendor/choosealicense.com/_licenses/blueoak-1.0.0.txt
vendor/choosealicense.com/_licenses/bsd-2-clause-patent.txt
vendor/choosealicense.com/_licenses/bsd-2-clause.txt
vendor/choosealicense.com/_licenses/bsd-3-clause-clear.txt
vendor/choosealicense.com/_licenses/bsd-3-clause.txt
vendor/choosealicense.com/_licenses/bsd-4-clause.txt
vendor/choosealicense.com/_licenses/bsl-1.0.txt
vendor/choosealicense.com/_licenses/cc-by-4.0.txt
vendor/choosealicense.com/_licenses/cc-by-sa-4.0.txt
vendor/choosealicense.com/_licenses/cc0-1.0.txt
vendor/choosealicense.com/_licenses/cecill-2.1.txt
vendor/choosealicense.com/_licenses/cern-ohl-p-2.0.txt
vendor/choosealicense.com/_licenses/cern-ohl-s-2.0.txt
vendor/choosealicense.com/_licenses/cern-ohl-w-2.0.txt
vendor/choosealicense.com/_licenses/ecl-2.0.txt
vendor/choosealicense.com/_licenses/epl-1.0.txt
vendor/choosealicense.com/_licenses/epl-2.0.txt
vendor/choosealicense.com/_licenses/eupl-1.1.txt
vendor/choosealicense.com/_licenses/eupl-1.2.txt
vendor/choosealicense.com/_licenses/gfdl-1.3.txt
vendor/choosealicense.com/_licenses/gpl-2.0.txt
owasp_depscan-6.0.0.dist-info/METADATA
owasp_depscan-6.0.0.dist-info/WHEEL
owasp_depscan-6.0.0.dist-info/entry_points.txt
owasp_depscan-6.0.0.dist-info/top_level.txt
owasp_depscan-6.0.0.dist-info/RECORD
