Metadata-Version: 2.4
Name: owasp-depscan
Version: 6.0.0
Summary: Fully open-source security audit for project dependencies based on known vulnerabilities and advisories.
Author-email: Team AppThreat <cloud@appthreat.com>
License-Expression: MIT
Project-URL: Homepage, https://github.com/owasp-dep-scan/dep-scan
Project-URL: Bug-Tracker, https://github.com/owasp-dep-scan/dep-scan/issues
Project-URL: Funding, https://owasp.org/donate/?reponame=www-project-dep-scan&title=OWASP+depscan
Classifier: Development Status :: 5 - Production/Stable
Classifier: Intended Audience :: Developers
Classifier: Intended Audience :: System Administrators
Classifier: Operating System :: OS Independent
Classifier: Programming Language :: Python :: 3.10
Classifier: Programming Language :: Python :: 3.11
Classifier: Programming Language :: Python :: 3.12
Classifier: Programming Language :: Python :: 3.13
Classifier: Topic :: Security
Classifier: Topic :: Utilities
Requires-Python: >=3.10
License-File: LICENSE
Requires-Dist: appthreat-vulnerability-db[oras]>=6.5.1
Requires-Dist: custom-json-diff>=2.1.6
Requires-Dist: defusedxml>=0.7.1
Requires-Dist: PyYAML>=6.0.2
Requires-Dist: rich>=14.0.0
Requires-Dist: Jinja2>=3.1.6
Requires-Dist: packageurl-python>=0.16.0
Requires-Dist: cvss>=3.4
Requires-Dist: tomli>=2.2.1; python_full_version <= "3.11"
Requires-Dist: ds-xbom-lib
Requires-Dist: ds-analysis-lib
Requires-Dist: ds-reporting-lib
Provides-Extra: dev
Requires-Dist: flake8>=7.1.2; extra == "dev"
Requires-Dist: pytest>=8.3.4; extra == "dev"
Requires-Dist: pytest-asyncio>=1.2.0; extra == "dev"
Requires-Dist: pytest-cov>=6.0.0; extra == "dev"
Requires-Dist: httpretty>=1.1.4; extra == "dev"
Provides-Extra: server
Requires-Dist: ds-server-lib; extra == "server"
Provides-Extra: ext
Requires-Dist: atom-tools>=0.7.8; extra == "ext"
Requires-Dist: blint>=3.0.6; extra == "ext"
Provides-Extra: perf
Requires-Dist: hishel[httpx]>=1.1.7; extra == "perf"
Provides-Extra: all
Requires-Dist: atom-tools>=0.7.8; extra == "all"
Requires-Dist: blint>=3.0.6; extra == "all"
Requires-Dist: ds-server-lib; extra == "all"
Requires-Dist: PyGithub>=2.6.1; extra == "all"
Requires-Dist: hishel[httpx]>=1.1.7; extra == "all"
Dynamic: license-file
